shuchu.py
shuchu-3.0.0.dist-info/licenses/LICENSE.txt
shuchu-3.0.0.dist-info/METADATA
shuchu-3.0.0.dist-info/WHEEL
shuchu-3.0.0.dist-info/top_level.txt
shuchu-3.0.0.dist-info/RECORD
